{"hierarchy":{"modules":[{"projects":[{"sections":[{"reference":"doc:\/\/Braze\/tutorials\/Braze\/a1-installation#Braze-Swift-Package","kind":"task"}],"reference":"doc:\/\/Braze\/tutorials\/Braze\/a1-installation"},{"sections":[{"reference":"doc:\/\/Braze\/tutorials\/Braze\/a2-configure-braze#The-Braze-instance","kind":"task"}],"reference":"doc:\/\/Braze\/tutorials\/Braze\/a2-configure-braze"},{"sections":[{"kind":"task","reference":"doc:\/\/Braze\/tutorials\/Braze\/a3-analytics#Identify-the-current-user"},{"kind":"task","reference":"doc:\/\/Braze\/tutorials\/Braze\/a3-analytics#Log-custom-events"},{"kind":"task","reference":"doc:\/\/Braze\/tutorials\/Braze\/a3-analytics#Log-purchases"}],"reference":"doc:\/\/Braze\/tutorials\/Braze\/a3-analytics"}],"reference":"doc:\/\/Braze\/tutorials\/00-integration-path\/Braze-Essentials"},{"projects":[{"sections":[{"kind":"task","reference":"doc:\/\/Braze\/tutorials\/Braze\/b1-standard-push-notifications#Setup-your-Xcode-project"},{"kind":"task","reference":"doc:\/\/Braze\/tutorials\/Braze\/b1-standard-push-notifications#Option-1-Automatic-push-notification-handling"},{"kind":"task","reference":"doc:\/\/Braze\/tutorials\/Braze\/b1-standard-push-notifications#Option-2-Implement-the-push-notification-handlers-manually"}],"reference":"doc:\/\/Braze\/tutorials\/Braze\/b1-standard-push-notifications"},{"sections":[{"kind":"task","reference":"doc:\/\/Braze\/tutorials\/Braze\/b2-rich-push-notifications#Notification-Service-Extension"}],"reference":"doc:\/\/Braze\/tutorials\/Braze\/b2-rich-push-notifications"},{"sections":[{"kind":"task","reference":"doc:\/\/Braze\/tutorials\/Braze\/b3-push-stories#Notification-Content-Extension"}],"reference":"doc:\/\/Braze\/tutorials\/Braze\/b3-push-stories"},{"sections":[{"reference":"doc:\/\/Braze\/tutorials\/Braze\/b4-live-activities#Creating-a-Live-Activity","kind":"task"},{"reference":"doc:\/\/Braze\/tutorials\/Braze\/b4-live-activities#Tracking-your-Live-Activity-with-Braze","kind":"task"},{"reference":"doc:\/\/Braze\/tutorials\/Braze\/b4-live-activities#Resuming-Live-Activity-tracking","kind":"task"},{"reference":"doc:\/\/Braze\/tutorials\/Braze\/b4-live-activities#Setting-up-push-to-start","kind":"task"},{"reference":"doc:\/\/Braze\/tutorials\/Braze\/b4-live-activities#Opting-out-of-push-to-start","kind":"task"}],"reference":"doc:\/\/Braze\/tutorials\/Braze\/b4-live-activities"}],"reference":"doc:\/\/Braze\/tutorials\/00-integration-path\/Push-Notifications"},{"projects":[{"reference":"doc:\/\/Braze\/tutorials\/Braze\/c1-inappmessageui","sections":[{"reference":"doc:\/\/Braze\/tutorials\/Braze\/c1-inappmessageui#BrazeInAppMessageUI","kind":"task"},{"reference":"doc:\/\/Braze\/tutorials\/Braze\/c1-inappmessageui#Optional-In-App-Message-UI-Delegate","kind":"task"}]},{"reference":"doc:\/\/Braze\/tutorials\/Braze\/c2-contentcardsui","sections":[{"reference":"doc:\/\/Braze\/tutorials\/Braze\/c2-contentcardsui#BrazeContentCardsUI","kind":"task"},{"reference":"doc:\/\/Braze\/tutorials\/Braze\/c2-contentcardsui#Optional-Content-Cards-customization","kind":"task"},{"reference":"doc:\/\/Braze\/tutorials\/Braze\/c2-contentcardsui#Optional-Content-Cards-view-controller-Delegate","kind":"task"}]},{"reference":"doc:\/\/Braze\/tutorials\/Braze\/c4-bannersui","sections":[{"reference":"doc:\/\/Braze\/tutorials\/Braze\/c4-bannersui#Option-1-BrazeBannersUI-in-UIKit","kind":"task"},{"reference":"doc:\/\/Braze\/tutorials\/Braze\/c4-bannersui#Option-2-BrazeBannersUI-in-SwiftUI","kind":"task"}]},{"reference":"doc:\/\/Braze\/tutorials\/Braze\/c3-gif-support","sections":[{"reference":"doc:\/\/Braze\/tutorials\/Braze\/c3-gif-support#Adding-GIF-support-with-SDWebImage","kind":"task"}]}],"reference":"doc:\/\/Braze\/tutorials\/00-integration-path\/User-Interface"},{"projects":[{"reference":"doc:\/\/Braze\/tutorials\/Braze\/d1-brazelocation","sections":[{"reference":"doc:\/\/Braze\/tutorials\/Braze\/d1-brazelocation#Setup-your-Xcode-project","kind":"task"},{"reference":"doc:\/\/Braze\/tutorials\/Braze\/d1-brazelocation#BrazeLocationProvider","kind":"task"}]}],"reference":"doc:\/\/Braze\/tutorials\/00-integration-path\/Location"},{"projects":[{"sections":[{"reference":"doc:\/\/Braze\/tutorials\/Braze\/e1-privacy-tracking#Prepare-your-app-for-App-Tracking-Transparency","kind":"task"},{"reference":"doc:\/\/Braze\/tutorials\/Braze\/e1-privacy-tracking#Configure-your-tracking-data","kind":"task"},{"reference":"doc:\/\/Braze\/tutorials\/Braze\/e1-privacy-tracking#Respond-to-App-Tracking-Transparency-permissions","kind":"task"},{"reference":"doc:\/\/Braze\/tutorials\/Braze\/e1-privacy-tracking#Updating-your-tracking-configurations-at-runtime","kind":"task"}],"reference":"doc:\/\/Braze\/tutorials\/Braze\/e1-privacy-tracking"}],"reference":"doc:\/\/Braze\/tutorials\/00-integration-path\/Privacy-Tracking"}],"reference":"doc:\/\/Braze\/tutorials\/00-integration-path","paths":[["doc:\/\/Braze\/tutorials\/00-integration-path","doc:\/\/Braze\/tutorials\/00-integration-path\/$volume","doc:\/\/Braze\/tutorials\/00-integration-path\/Push-Notifications"],["doc:\/\/Braze\/documentation\/BrazeKit"]]},"variants":[{"paths":["\/tutorials\/braze\/b4-live-activities"],"traits":[{"interfaceLanguage":"swift"}]}],"sections":[{"kind":"hero","estimatedTimeInMinutes":10,"title":"Live Activities","chapter":"Push Notifications","content":[{"type":"paragraph","inlineContent":[{"type":"text","text":"Learn how to remotely track and manage your iOS "},{"identifier":"https:\/\/developer.apple.com\/documentation\/activitykit\/updating-and-ending-your-live-activity-with-activitykit-push-notifications","type":"reference","isActive":true},{"type":"text","text":" with Braze push notifications."}]}]},{"kind":"tasks","tasks":[{"contentSection":[{"content":[{"type":"paragraph","inlineContent":[{"type":"text","text":"In this section, we describe the prerequisite steps to create a Live Activity you wish to register with Braze."}]}],"mediaPosition":"trailing","kind":"contentAndMedia"}],"stepsSection":[{"code":"b4-01.swift","content":[{"type":"paragraph","inlineContent":[{"type":"text","text":"First ensure that you have followed "},{"type":"reference","identifier":"https:\/\/developer.apple.com\/documentation\/activitykit\/displaying-live-data-with-live-activities","isActive":true},{"type":"text","text":" in Apple’s documentation to set up Live Activities in your application. Also, ensure that your app is using a "},{"inlineContent":[{"type":"codeVoice","code":".p8"},{"type":"text","text":" key"}],"type":"strong"},{"type":"text","text":" to send push notifications."}]}],"media":null,"runtimePreview":null,"caption":[{"type":"paragraph","inlineContent":[{"type":"text","text":"For this example, we have created a struct called "},{"code":"BasketballActivityAttributes","type":"codeVoice"},{"type":"text","text":", but you may use your own implementation of "},{"type":"reference","identifier":"https:\/\/developer.apple.com\/documentation\/activitykit\/activityattributes","isActive":true},{"type":"text","text":"."}]}],"type":"step"}],"anchor":"Creating-a-Live-Activity","title":"Creating a Live Activity"},{"contentSection":[{"mediaPosition":"trailing","kind":"contentAndMedia","content":[{"type":"paragraph","inlineContent":[{"type":"text","text":"This section dives into the interface methods Braze provides to track and manage your Live Activities."}]}]}],"stepsSection":[{"runtimePreview":null,"caption":[],"type":"step","media":null,"code":"b4-02.swift","content":[{"type":"paragraph","inlineContent":[{"type":"text","text":"Create a class to interface with the Live Activity objects."}]}]},{"runtimePreview":null,"caption":[{"type":"paragraph","inlineContent":[{"type":"text","text":"Note that the method and parameters to create a Live Activity may differ depending on the version of iOS you are targeting, but Braze accepts "},{"type":"reference","isActive":true,"identifier":"https:\/\/developer.apple.com\/documentation\/activitykit\/activity"},{"type":"text","text":" objects of any type created with iOS "},{"type":"strong","inlineContent":[{"text":"16.1","type":"text"}]},{"type":"text","text":" and up."}]}],"type":"step","media":null,"code":"b4-03.swift","content":[{"type":"paragraph","inlineContent":[{"type":"text","text":"Inside this class, create an instance of your Live Activity implementation using Apple’s ActivityKit APIs. Request your Activity with the "},{"code":"pushType","type":"codeVoice"},{"type":"text","text":" parameter set to "},{"code":".token","type":"codeVoice"},{"type":"text","text":"."}]}]},{"runtimePreview":null,"caption":[{"inlineContent":[{"type":"text","text":"The "},{"type":"strong","inlineContent":[{"type":"text","text":"pushTokenTag"}]},{"type":"text","text":" parameter is a custom string you define. It should be unique for each Live Activity you create."}],"type":"paragraph"}],"type":"step","media":null,"code":"b4-04.swift","content":[{"inlineContent":[{"type":"text","text":"Register your "},{"type":"codeVoice","code":"Activity"},{"type":"text","text":" with your Braze instance by passing it into "},{"type":"codeVoice","code":"launchActivity(pushTokenTag:activity:)"},{"type":"text","text":"."}],"type":"paragraph"}]}],"anchor":"Tracking-your-Live-Activity-with-Braze","title":"Tracking your Live Activity with Braze"},{"contentSection":[{"kind":"contentAndMedia","mediaPosition":"trailing","content":[{"type":"paragraph","inlineContent":[{"type":"text","text":"In this section, we demonstrate how to resume Live Activity tracking upon app launch. This allows Braze to resume tracking push token updates for all active Live Activities."}]}]}],"stepsSection":[{"media":null,"type":"step","code":"b4-05.swift","caption":[],"runtimePreview":null,"content":[{"type":"paragraph","inlineContent":[{"text":"Open your ","type":"text"},{"type":"strong","inlineContent":[{"text":"AppDelegate","type":"text"}]},{"text":" file.","type":"text"}]}]},{"media":null,"type":"step","code":"b4-06.swift","caption":[],"runtimePreview":null,"content":[{"type":"paragraph","inlineContent":[{"type":"text","text":"Import the "},{"type":"codeVoice","code":"ActivityKit"},{"type":"text","text":" module if it’s available."}]}]},{"media":null,"type":"step","code":"b4-07.swift","caption":[],"runtimePreview":null,"content":[{"inlineContent":[{"type":"text","text":"Call "},{"code":"resumeActivities(ofType:)","type":"codeVoice"},{"text":" in ","type":"text"},{"code":"application(_:didFinishLaunchingWithOptions:)","type":"codeVoice"},{"text":" for all ","type":"text"},{"code":"ActivityAttributes","type":"codeVoice"},{"text":" types you have registered in your application.","type":"text"}],"type":"paragraph"}]}],"anchor":"Resuming-Live-Activity-tracking","title":"Resuming Live Activity tracking"},{"contentSection":[{"mediaPosition":"trailing","kind":"contentAndMedia","content":[{"inlineContent":[{"type":"text","text":"This section shows how to equip your app to start Live Activities via push notifications. Note that push-to-start requires iOS 17.2 or higher."}],"type":"paragraph"}]}],"stepsSection":[{"type":"step","media":"b4-frameworks.png","runtimePreview":null,"caption":[],"content":[{"inlineContent":[{"type":"text","text":"In your Xcode project, add "},{"type":"codeVoice","code":"BrazeKit"},{"type":"text","text":" to your Live Activity widget extension’s "},{"type":"codeVoice","code":"Frameworks and Libraries"},{"type":"text","text":"."}],"type":"paragraph"}],"code":null},{"type":"step","media":null,"runtimePreview":null,"caption":[],"content":[{"inlineContent":[{"text":"Return to your Live Activity ","type":"text"},{"type":"codeVoice","code":"ActivityAttributes"},{"text":" implementation.","type":"text"}],"type":"paragraph"}],"code":"b4-08.swift"},{"type":"step","media":null,"runtimePreview":null,"caption":[],"content":[{"type":"paragraph","inlineContent":[{"type":"text","text":"Import "},{"type":"codeVoice","code":"BrazeKit"},{"type":"text","text":" and conform your attributes struct to "},{"type":"codeVoice","code":"BrazeLiveActivityAttributes"},{"type":"text","text":" in addition to "},{"type":"codeVoice","code":"ActivityAttributes"},{"type":"text","text":"."}]}],"code":"b4-09.swift"},{"type":"step","media":null,"runtimePreview":null,"caption":[{"inlineContent":[{"text":"This property will be mapped directly to the ","type":"text"},{"code":"\"brazeActivityId\"","type":"codeVoice"},{"text":" field in the Live Activity push-to-start payload, which is inserted automatically by the Braze sender service. It should not be renamed or assigned to any other value.","type":"text"}],"type":"paragraph"}],"content":[{"inlineContent":[{"type":"text","text":"The "},{"type":"codeVoice","code":"BrazeLiveActivityAttributes"},{"type":"text","text":" interface includes the "},{"type":"codeVoice","code":"brazeActivityId"},{"type":"text","text":" property as a "},{"type":"codeVoice","code":"String?"},{"type":"text","text":" type. Add a declaration of this property to your struct definition."}],"type":"paragraph"}],"code":"b4-10.swift"},{"type":"step","media":null,"runtimePreview":null,"caption":[],"content":[{"inlineContent":[{"text":"Return to your ","type":"text"},{"type":"strong","inlineContent":[{"type":"text","text":"AppDelegate.swift"}]},{"text":" file.","type":"text"}],"type":"paragraph"}],"code":"b4-11.swift"},{"type":"step","media":null,"runtimePreview":null,"caption":[{"type":"paragraph","inlineContent":[{"text":"This method returns a Swift ","type":"text"},{"code":"Task","type":"codeVoice"},{"text":", which you may retain in your application if you ever need to cancel it. This task allows Braze to register your Live Activity’s push-to-start token and respond to any remotely started activities.","type":"text"}]}],"content":[{"type":"paragraph","inlineContent":[{"text":"Call ","type":"text"},{"code":"registerPushToStart(forType:name:)","type":"codeVoice"},{"text":" for any number of ","type":"text"},{"code":"ActivityAttributes","type":"codeVoice"},{"text":" types you have registered in your application. You can call this method anywhere in your code, but to ensure that the registration is processed prior to other logic, we call it in ","type":"text"},{"code":"application(_:didFinishLaunchingWithOptions:)","type":"codeVoice"},{"text":".","type":"text"}]}],"code":"b4-12.swift"}],"anchor":"Setting-up-push-to-start","title":"Setting up push-to-start"},{"contentSection":[{"content":[{"type":"paragraph","inlineContent":[{"type":"text","text":"This section shows how to opt a user out of receiving push-to-start notifications for a given Live Activity type if they have previously registered."}]}],"kind":"contentAndMedia","mediaPosition":"trailing"}],"stepsSection":[{"content":[{"inlineContent":[{"text":"In our example, we’ll return to our ","type":"text"},{"type":"codeVoice","code":"LiveActivityManager"},{"text":" class.","type":"text"}],"type":"paragraph"}],"type":"step","code":"b4-13.swift","caption":[],"media":null,"runtimePreview":null},{"content":[{"type":"paragraph","inlineContent":[{"type":"text","text":"Call "},{"type":"codeVoice","code":"optOutPushToStart(type:)"},{"type":"text","text":", passing in the string of a given Live Activity attributes type. You may call this method wherever it is appropriate for your use case."}]}],"type":"step","code":"b4-14.swift","caption":[{"type":"paragraph","inlineContent":[{"text":"If you have a running ","type":"text"},{"code":"Task","type":"codeVoice"},{"text":" from a prior call of ","type":"text"},{"code":"registerPushToStart(forType:name:)","type":"codeVoice"},{"text":", be sure to cancel that task whenever you opt out. Your user will no longer receive push-to-start notifications for that type.","type":"text"}]}],"media":null,"runtimePreview":null},{"content":[{"type":"paragraph","inlineContent":[{"type":"text","text":"In the future, if you ever wish to opt in that user again, simply repeat the steps in "},{"type":"strong","inlineContent":[{"type":"text","text":"Setting up push-to-start"}]},{"type":"text","text":"."}]}],"type":"step","code":null,"caption":[],"media":null,"runtimePreview":null}],"anchor":"Opting-out-of-push-to-start","title":"Opting out of push-to-start"}]},{"kind":"callToAction","action":{"type":"reference","overridingTitle":"Get started","identifier":"doc:\/\/Braze\/tutorials\/Braze\/c1-inappmessageui","overridingTitleInlineContent":[{"type":"text","text":"Get started"}],"isActive":true},"title":"In-App Message UI","featuredEyebrow":"Tutorial","abstract":[{"type":"text","text":"Learn how to display "},{"type":"reference","identifier":"https:\/\/www.braze.com\/docs\/user_guide\/message_building_by_channel\/in-app_messages","isActive":true},{"type":"text","text":" to your users using the Braze provided user interface."}]}],"kind":"project","schemaVersion":{"minor":3,"patch":0,"major":0},"metadata":{"role":"project","categoryPathComponent":"00-integration-path","title":"Live Activities","category":"Braze"},"identifier":{"interfaceLanguage":"swift","url":"doc:\/\/Braze\/tutorials\/Braze\/b4-live-activities"},"references":{"b4-08.swift":{"type":"file","fileType":"swift","content":["#if canImport(ActivityKit)","  import ActivityKit","#endif","","@available(iOS 16.1, *)","struct BasketballActivityAttributes: ActivityAttributes {","  public struct ContentState: Codable, Hashable {","    var team1Score: Int","    var team2Score: Int","  }","","  var team1Name: String","  var team2Name: String","}"],"fileName":"BasketballActivityAttributes.swift","identifier":"b4-08.swift","highlights":[],"syntax":"swift"},"doc://Braze/tutorials/Braze/a2-configure-braze#The-Braze-instance":{"url":"\/tutorials\/braze\/a2-configure-braze#The-Braze-instance","type":"section","role":"pseudoSymbol","abstract":[{"type":"text","text":"Create and configure the Braze instance."}],"kind":"section","title":"The Braze instance","identifier":"doc:\/\/Braze\/tutorials\/Braze\/a2-configure-braze#The-Braze-instance"},"doc://Braze/tutorials/Braze/d1-brazelocation#Setup-your-Xcode-project":{"title":"Setup your Xcode project","url":"\/tutorials\/braze\/d1-brazelocation#Setup-your-Xcode-project","role":"pseudoSymbol","abstract":[{"type":"text","text":"Learn how to implement "},{"type":"reference","isActive":true,"identifier":"https:\/\/www.braze.com\/docs\/user_guide\/engagement_tools\/locations_and_geofences\/"},{"type":"text","text":" using the "},{"type":"strong","inlineContent":[{"text":"BrazeLocation","type":"text"}]},{"type":"text","text":" module."}],"type":"section","kind":"section","identifier":"doc:\/\/Braze\/tutorials\/Braze\/d1-brazelocation#Setup-your-Xcode-project"},"doc://Braze/tutorials/Braze/e1-privacy-tracking#Updating-your-tracking-configurations-at-runtime":{"identifier":"doc:\/\/Braze\/tutorials\/Braze\/e1-privacy-tracking#Updating-your-tracking-configurations-at-runtime","title":"Updating your tracking configurations at runtime","role":"pseudoSymbol","abstract":[{"type":"text","text":"Learn how to manage your data collection practices for tracking."}],"kind":"section","type":"section","url":"\/tutorials\/braze\/e1-privacy-tracking#Updating-your-tracking-configurations-at-runtime"},"doc://Braze/tutorials/Braze/b1-standard-push-notifications#Setup-your-Xcode-project":{"type":"section","abstract":[{"type":"text","text":"Learn how to support receiving foreground and background push notifications."}],"title":"Setup your Xcode project","role":"pseudoSymbol","url":"\/tutorials\/braze\/b1-standard-push-notifications#Setup-your-Xcode-project","identifier":"doc:\/\/Braze\/tutorials\/Braze\/b1-standard-push-notifications#Setup-your-Xcode-project","kind":"section"},"doc://Braze/tutorials/Braze/c3-gif-support#Adding-GIF-support-with-SDWebImage":{"identifier":"doc:\/\/Braze\/tutorials\/Braze\/c3-gif-support#Adding-GIF-support-with-SDWebImage","url":"\/tutorials\/braze\/c3-gif-support#Adding-GIF-support-with-SDWebImage","abstract":[{"type":"text","text":"Learn how to add GIF images support to Braze provided user interface using third party libraries."}],"title":"Adding GIF support with SDWebImage","role":"pseudoSymbol","type":"section","kind":"section"},"b4-01.swift":{"content":["#if canImport(ActivityKit)","  import ActivityKit","#endif","","@available(iOS 16.1, *)","struct BasketballActivityAttributes: ActivityAttributes {","  public struct ContentState: Codable, Hashable {","    var team1Score: Int","    var team2Score: Int","  }","","  var team1Name: String","  var team2Name: String","}"],"identifier":"b4-01.swift","highlights":[],"type":"file","fileName":"BasketballActivityAttributes.swift","syntax":"swift","fileType":"swift"},"doc://Braze/tutorials/Braze/a3-analytics#Identify-the-current-user":{"role":"pseudoSymbol","kind":"section","identifier":"doc:\/\/Braze\/tutorials\/Braze\/a3-analytics#Identify-the-current-user","type":"section","url":"\/tutorials\/braze\/a3-analytics#Identify-the-current-user","title":"Identify the current user","abstract":[{"type":"text","text":"Learn how to log user attributes, custom events, purchases."}]},"doc://Braze/tutorials/Braze/c4-bannersui#Option-2-BrazeBannersUI-in-SwiftUI":{"url":"\/tutorials\/braze\/c4-bannersui#Option-2-BrazeBannersUI-in-SwiftUI","kind":"section","type":"section","identifier":"doc:\/\/Braze\/tutorials\/Braze\/c4-bannersui#Option-2-BrazeBannersUI-in-SwiftUI","title":"Option 2: BrazeBannersUI in SwiftUI","abstract":[{"text":"Learn how to display Banners to your users using the Braze provided user interface. This example showcases how to add Banners to your app using either UIKit (Option 1) or SwiftUI (Option 2).","type":"text"}],"role":"pseudoSymbol"},"doc://Braze/tutorials/00-integration-path/Braze-Essentials":{"url":"\/tutorials\/00-integration-path\/braze-essentials","title":"Braze Essentials","identifier":"doc:\/\/Braze\/tutorials\/00-integration-path\/Braze-Essentials","kind":"article","role":"article","type":"topic","abstract":[]},"b4-10.swift":{"type":"file","syntax":"swift","identifier":"b4-10.swift","content":["#if canImport(ActivityKit)","  import ActivityKit","#endif","","import BrazeKit","","@available(iOS 16.1, *)","struct BasketballActivityAttributes: ActivityAttributes, BrazeLiveActivityAttributes {","  public struct ContentState: Codable, Hashable {","    var team1Score: Int","    var team2Score: Int","  }","","  var team1Name: String","  var team2Name: String","  var brazeActivityId: String?","}"],"fileType":"swift","fileName":"BasketballActivityAttributes.swift","highlights":[]},"doc://Braze/tutorials/Braze/e1-privacy-tracking#Configure-your-tracking-data":{"title":"Configure your tracking data","url":"\/tutorials\/braze\/e1-privacy-tracking#Configure-your-tracking-data","identifier":"doc:\/\/Braze\/tutorials\/Braze\/e1-privacy-tracking#Configure-your-tracking-data","abstract":[{"text":"Learn how to manage your data collection practices for tracking.","type":"text"}],"kind":"section","type":"section","role":"pseudoSymbol"},"doc://Braze/tutorials/Braze/c1-inappmessageui#Optional-In-App-Message-UI-Delegate":{"title":"Optional: In-App Message UI Delegate","url":"\/tutorials\/braze\/c1-inappmessageui#Optional-In-App-Message-UI-Delegate","type":"section","role":"pseudoSymbol","kind":"section","identifier":"doc:\/\/Braze\/tutorials\/Braze\/c1-inappmessageui#Optional-In-App-Message-UI-Delegate","abstract":[{"text":"Learn how to display ","type":"text"},{"identifier":"https:\/\/www.braze.com\/docs\/user_guide\/message_building_by_channel\/in-app_messages","isActive":true,"type":"reference"},{"text":" to your users using the Braze provided user interface.","type":"text"}]},"doc://Braze/tutorials/Braze/c2-contentcardsui":{"estimatedTime":"10min","abstract":[{"type":"text","text":"Learn how to display "},{"type":"reference","identifier":"https:\/\/www.braze.com\/docs\/user_guide\/message_building_by_channel\/content_cards\/","isActive":true},{"type":"text","text":" to your users using the Braze provided user interface."}],"identifier":"doc:\/\/Braze\/tutorials\/Braze\/c2-contentcardsui","kind":"project","title":"Content Cards UI","url":"\/tutorials\/braze\/c2-contentcardsui","type":"topic","role":"project"},"doc://Braze/tutorials/Braze/e1-privacy-tracking":{"title":"Privacy Tracking Data","role":"project","abstract":[{"text":"Learn how to manage your data collection practices for tracking.","type":"text"}],"kind":"project","url":"\/tutorials\/braze\/e1-privacy-tracking","estimatedTime":"10min","type":"topic","identifier":"doc:\/\/Braze\/tutorials\/Braze\/e1-privacy-tracking"},"b4-13.swift":{"highlights":[],"syntax":"swift","content":["class LiveActivityManager {","  ","}"],"fileType":"swift","type":"file","identifier":"b4-13.swift","fileName":"LiveActivityManager.swift"},"doc://Braze/tutorials/Braze/a3-analytics":{"kind":"project","url":"\/tutorials\/braze\/a3-analytics","type":"topic","abstract":[{"text":"Learn how to log user attributes, custom events, purchases.","type":"text"}],"estimatedTime":"15min","title":"Analytics","identifier":"doc:\/\/Braze\/tutorials\/Braze\/a3-analytics","role":"project"},"doc://Braze/tutorials/Braze/c1-inappmessageui#BrazeInAppMessageUI":{"title":"BrazeInAppMessageUI","url":"\/tutorials\/braze\/c1-inappmessageui#BrazeInAppMessageUI","kind":"section","role":"pseudoSymbol","abstract":[{"type":"text","text":"Learn how to display "},{"type":"reference","identifier":"https:\/\/www.braze.com\/docs\/user_guide\/message_building_by_channel\/in-app_messages","isActive":true},{"type":"text","text":" to your users using the Braze provided user interface."}],"type":"section","identifier":"doc:\/\/Braze\/tutorials\/Braze\/c1-inappmessageui#BrazeInAppMessageUI"},"https://developer.apple.com/documentation/activitykit/activityattributes":{"identifier":"https:\/\/developer.apple.com\/documentation\/activitykit\/activityattributes","url":"https:\/\/developer.apple.com\/documentation\/activitykit\/activityattributes","titleInlineContent":[{"code":"ActivityAttributes","type":"codeVoice"}],"title":"ActivityAttributes","type":"link"},"b4-03.swift":{"content":["#if canImport(ActivityKit)","  import ActivityKit","#endif","","class LiveActivityManager {","  ","  @available(iOS 16.2, *)","  func createActivity() {","    let activityAttributes = BasketballActivityAttributes(team1Name: \"Team 1\", team2Name: \"Team 2\")","    let contentState = BasketballActivityAttributes.ContentState(team1Score: 0, team2Score: 0)","    let activityContent = ActivityContent(state: contentState, staleDate: nil)","    \/\/ Ensure that your Live Activity is created with the `pushType` parameter set to `.token`.","    if let activity = try? Activity.request(attributes: activityAttributes,","                                            content: activityContent,","                                            pushType: .token) {","      ","    }","  }","  ","}"],"fileType":"swift","type":"file","identifier":"b4-03.swift","syntax":"swift","highlights":[],"fileName":"LiveActivityManager.swift"},"b4-05.swift":{"highlights":[],"identifier":"b4-05.swift","fileType":"swift","syntax":"swift","content":["import UIKit","import BrazeKit","","@main","class AppDelegate: UIResponder, UIApplicationDelegate {","","  static var braze: Braze? = nil","","  func application(","    _ application: UIApplication,","    didFinishLaunchingWithOptions launchOptions: [UIApplication.LaunchOptionsKey: Any]?","  ) -> Bool {","","    return true","  }","}"],"fileName":"AppDelegate.swift","type":"file"},"doc://Braze/tutorials/Braze/b4-live-activities#Opting-out-of-push-to-start":{"url":"\/tutorials\/braze\/b4-live-activities#Opting-out-of-push-to-start","role":"pseudoSymbol","type":"section","title":"Opting out of push-to-start","kind":"section","abstract":[{"type":"text","text":"Learn how to remotely track and manage your iOS "},{"type":"reference","isActive":true,"identifier":"https:\/\/developer.apple.com\/documentation\/activitykit\/updating-and-ending-your-live-activity-with-activitykit-push-notifications"},{"type":"text","text":" with Braze push notifications."}],"identifier":"doc:\/\/Braze\/tutorials\/Braze\/b4-live-activities#Opting-out-of-push-to-start"},"doc://Braze/tutorials/Braze/a3-analytics#Log-purchases":{"abstract":[{"type":"text","text":"Learn how to log user attributes, custom events, purchases."}],"identifier":"doc:\/\/Braze\/tutorials\/Braze\/a3-analytics#Log-purchases","role":"pseudoSymbol","type":"section","url":"\/tutorials\/braze\/a3-analytics#Log-purchases","kind":"section","title":"Log purchases"},"b4-11.swift":{"identifier":"b4-11.swift","highlights":[],"fileName":"AppDelegate.swift","syntax":"swift","type":"file","content":["import UIKit","import BrazeKit","","#if canImport(ActivityKit)","  import ActivityKit","#endif","","@main","class AppDelegate: UIResponder, UIApplicationDelegate {","","  static var braze: Braze? = nil","","  func application(","    _ application: UIApplication,","    didFinishLaunchingWithOptions launchOptions: [UIApplication.LaunchOptionsKey: Any]?","  ) -> Bool {","    ","    if #available(iOS 16.1, *) {","      Self.braze?.liveActivities.resumeActivities(","        ofType: Activity<BasketballActivityAttributes>.self","      )","    }","","    return true","  }","}"],"fileType":"swift"},"doc://Braze/tutorials/Braze/b2-rich-push-notifications":{"role":"project","url":"\/tutorials\/braze\/b2-rich-push-notifications","title":"Rich Push Notifications","type":"topic","kind":"project","estimatedTime":"5min","identifier":"doc:\/\/Braze\/tutorials\/Braze\/b2-rich-push-notifications","abstract":[{"type":"text","text":"Learn how to support receiving rich push notifications with images, audio and video."}]},"https://developer.apple.com/documentation/activitykit/displaying-live-data-with-live-activities":{"type":"link","identifier":"https:\/\/developer.apple.com\/documentation\/activitykit\/displaying-live-data-with-live-activities","title":"Displaying live data with Live Activities","titleInlineContent":[{"text":"Displaying live data with Live Activities","type":"text"}],"url":"https:\/\/developer.apple.com\/documentation\/activitykit\/displaying-live-data-with-live-activities"},"doc://Braze/tutorials/Braze/b1-standard-push-notifications":{"role":"project","url":"\/tutorials\/braze\/b1-standard-push-notifications","identifier":"doc:\/\/Braze\/tutorials\/Braze\/b1-standard-push-notifications","abstract":[{"text":"Learn how to support receiving foreground and background push notifications.","type":"text"}],"title":"Standard Push Notifications","kind":"project","estimatedTime":"20min","type":"topic"},"doc://Braze/tutorials/Braze/b3-push-stories#Notification-Content-Extension":{"type":"section","title":"Notification Content Extension","identifier":"doc:\/\/Braze\/tutorials\/Braze\/b3-push-stories#Notification-Content-Extension","kind":"section","abstract":[{"type":"text","text":"Learn how to support receiving "},{"identifier":"https:\/\/www.braze.com\/docs\/user_guide\/message_building_by_channel\/push\/advanced_push_options\/push_stories\/","isActive":true,"type":"reference"},{"type":"text","text":" notifications."}],"url":"\/tutorials\/braze\/b3-push-stories#Notification-Content-Extension","role":"pseudoSymbol"},"doc://Braze/tutorials/Braze/d1-brazelocation":{"type":"topic","title":"Locations and Geofences","url":"\/tutorials\/braze\/d1-brazelocation","kind":"project","abstract":[{"text":"Learn how to implement ","type":"text"},{"identifier":"https:\/\/www.braze.com\/docs\/user_guide\/engagement_tools\/locations_and_geofences\/","type":"reference","isActive":true},{"text":" using the ","type":"text"},{"inlineContent":[{"text":"BrazeLocation","type":"text"}],"type":"strong"},{"text":" module.","type":"text"}],"role":"project","estimatedTime":"10min","identifier":"doc:\/\/Braze\/tutorials\/Braze\/d1-brazelocation"},"b4-06.swift":{"fileType":"swift","content":["import UIKit","import BrazeKit","","#if canImport(ActivityKit)","  import ActivityKit","#endif","","@main","class AppDelegate: UIResponder, UIApplicationDelegate {","","  static var braze: Braze? = nil","","  func application(","    _ application: UIApplication,","    didFinishLaunchingWithOptions launchOptions: [UIApplication.LaunchOptionsKey: Any]?","  ) -> Bool {","","    return true","  }","}"],"type":"file","highlights":[],"fileName":"AppDelegate.swift","identifier":"b4-06.swift","syntax":"swift"},"b4-frameworks.png":{"alt":"Widget extension Frameworks and Libraries","identifier":"b4-frameworks.png","variants":[{"url":"\/images\/Braze\/b4-frameworks.png","traits":["1x","light"]},{"url":"\/images\/Braze\/b4-frameworks~dark.png","traits":["1x","dark"]}],"type":"image"},"https://www.braze.com/docs/user_guide/message_building_by_channel/in-app_messages":{"type":"link","identifier":"https:\/\/www.braze.com\/docs\/user_guide\/message_building_by_channel\/in-app_messages","title":"In-App Messages","titleInlineContent":[{"text":"In-App Messages","type":"text"}],"url":"https:\/\/www.braze.com\/docs\/user_guide\/message_building_by_channel\/in-app_messages"},"doc://Braze/tutorials/Braze/c3-gif-support":{"kind":"project","role":"project","title":"GIF Support","estimatedTime":"5min","type":"topic","identifier":"doc:\/\/Braze\/tutorials\/Braze\/c3-gif-support","url":"\/tutorials\/braze\/c3-gif-support","abstract":[{"text":"Learn how to add GIF images support to Braze provided user interface using third party libraries.","type":"text"}]},"doc://Braze/tutorials/00-integration-path":{"url":"\/tutorials\/00-integration-path","type":"topic","title":"Integration Path","identifier":"doc:\/\/Braze\/tutorials\/00-integration-path","abstract":[{"type":"text","text":"Follow these step by step tutorials to learn how to get the most out of the Braze SDK."}],"kind":"overview","role":"overview"},"doc://Braze/tutorials/Braze/b4-live-activities#Setting-up-push-to-start":{"role":"pseudoSymbol","kind":"section","url":"\/tutorials\/braze\/b4-live-activities#Setting-up-push-to-start","identifier":"doc:\/\/Braze\/tutorials\/Braze\/b4-live-activities#Setting-up-push-to-start","type":"section","abstract":[{"text":"Learn how to remotely track and manage your iOS ","type":"text"},{"type":"reference","isActive":true,"identifier":"https:\/\/developer.apple.com\/documentation\/activitykit\/updating-and-ending-your-live-activity-with-activitykit-push-notifications"},{"text":" with Braze push notifications.","type":"text"}],"title":"Setting up push-to-start"},"b4-09.swift":{"fileName":"BasketballActivityAttributes.swift","identifier":"b4-09.swift","syntax":"swift","highlights":[],"type":"file","content":["#if canImport(ActivityKit)","  import ActivityKit","#endif","","import BrazeKit","","@available(iOS 16.1, *)","struct BasketballActivityAttributes: ActivityAttributes, BrazeLiveActivityAttributes {","  public struct ContentState: Codable, Hashable {","    var team1Score: Int","    var team2Score: Int","  }","","  var team1Name: String","  var team2Name: String","}"],"fileType":"swift"},"doc://Braze/tutorials/00-integration-path/Push-Notifications":{"url":"\/tutorials\/00-integration-path\/push-notifications","type":"topic","identifier":"doc:\/\/Braze\/tutorials\/00-integration-path\/Push-Notifications","abstract":[],"role":"article","title":"Push Notifications","kind":"article"},"b4-12.swift":{"type":"file","fileType":"swift","identifier":"b4-12.swift","syntax":"swift","fileName":"AppDelegate.swift","highlights":[],"content":["import UIKit","import BrazeKit","","#if canImport(ActivityKit)","  import ActivityKit","#endif","","@main","class AppDelegate: UIResponder, UIApplicationDelegate {","","  static var braze: Braze? = nil","","  func application(","    _ application: UIApplication,","    didFinishLaunchingWithOptions launchOptions: [UIApplication.LaunchOptionsKey: Any]?","  ) -> Bool {","    ","    if #available(iOS 16.1, *) {","      Self.braze?.liveActivities.resumeActivities(","        ofType: Activity<BasketballActivityAttributes>.self","      )","    }","    ","    if #available(iOS 17.2, *) {","      let pushToStartObserver: Task = Self.braze?.liveActivities.registerPushToStart(","        forType: Activity<BasketballActivityAttributes>.self,","        name: \"BasketballActivityAttributes\")","    }","","    return true","  }","}"]},"doc://Braze/tutorials/Braze/e1-privacy-tracking#Prepare-your-app-for-App-Tracking-Transparency":{"title":"Prepare your app for App Tracking Transparency","identifier":"doc:\/\/Braze\/tutorials\/Braze\/e1-privacy-tracking#Prepare-your-app-for-App-Tracking-Transparency","type":"section","abstract":[{"type":"text","text":"Learn how to manage your data collection practices for tracking."}],"kind":"section","url":"\/tutorials\/braze\/e1-privacy-tracking#Prepare-your-app-for-App-Tracking-Transparency","role":"pseudoSymbol"},"doc://Braze/tutorials/Braze/a2-configure-braze":{"kind":"project","identifier":"doc:\/\/Braze\/tutorials\/Braze\/a2-configure-braze","url":"\/tutorials\/braze\/a2-configure-braze","title":"Configure Braze","type":"topic","abstract":[{"text":"Create and configure the Braze instance.","type":"text"}],"estimatedTime":"5min","role":"project"},"doc://Braze/tutorials/Braze/c4-bannersui#Option-1-BrazeBannersUI-in-UIKit":{"title":"Option 1: BrazeBannersUI in UIKit","abstract":[{"text":"Learn how to display Banners to your users using the Braze provided user interface. This example showcases how to add Banners to your app using either UIKit (Option 1) or SwiftUI (Option 2).","type":"text"}],"url":"\/tutorials\/braze\/c4-bannersui#Option-1-BrazeBannersUI-in-UIKit","kind":"section","identifier":"doc:\/\/Braze\/tutorials\/Braze\/c4-bannersui#Option-1-BrazeBannersUI-in-UIKit","role":"pseudoSymbol","type":"section"},"doc://Braze/tutorials/Braze/b1-standard-push-notifications#Option-2-Implement-the-push-notification-handlers-manually":{"role":"pseudoSymbol","kind":"section","type":"section","title":"Option 2: Implement the push notification handlers manually","identifier":"doc:\/\/Braze\/tutorials\/Braze\/b1-standard-push-notifications#Option-2-Implement-the-push-notification-handlers-manually","abstract":[{"text":"Learn how to support receiving foreground and background push notifications.","type":"text"}],"url":"\/tutorials\/braze\/b1-standard-push-notifications#Option-2-Implement-the-push-notification-handlers-manually"},"doc://Braze/tutorials/Braze/b4-live-activities":{"kind":"project","type":"topic","title":"Live Activities","url":"\/tutorials\/braze\/b4-live-activities","abstract":[{"type":"text","text":"Learn how to remotely track and manage your iOS "},{"type":"reference","identifier":"https:\/\/developer.apple.com\/documentation\/activitykit\/updating-and-ending-your-live-activity-with-activitykit-push-notifications","isActive":true},{"type":"text","text":" with Braze push notifications."}],"role":"project","estimatedTime":"10min","identifier":"doc:\/\/Braze\/tutorials\/Braze\/b4-live-activities"},"doc://Braze/tutorials/00-integration-path/Privacy-Tracking":{"title":"Privacy Tracking","role":"article","kind":"article","url":"\/tutorials\/00-integration-path\/privacy-tracking","identifier":"doc:\/\/Braze\/tutorials\/00-integration-path\/Privacy-Tracking","type":"topic","abstract":[]},"doc://Braze/tutorials/Braze/b3-push-stories":{"kind":"project","url":"\/tutorials\/braze\/b3-push-stories","title":"Push Stories","type":"topic","role":"project","identifier":"doc:\/\/Braze\/tutorials\/Braze\/b3-push-stories","abstract":[{"type":"text","text":"Learn how to support receiving "},{"isActive":true,"type":"reference","identifier":"https:\/\/www.braze.com\/docs\/user_guide\/message_building_by_channel\/push\/advanced_push_options\/push_stories\/"},{"type":"text","text":" notifications."}],"estimatedTime":"20min"},"doc://Braze/tutorials/Braze/b1-standard-push-notifications#Option-1-Automatic-push-notification-handling":{"abstract":[{"text":"Learn how to support receiving foreground and background push notifications.","type":"text"}],"identifier":"doc:\/\/Braze\/tutorials\/Braze\/b1-standard-push-notifications#Option-1-Automatic-push-notification-handling","kind":"section","title":"Option 1: Automatic push notification handling","type":"section","url":"\/tutorials\/braze\/b1-standard-push-notifications#Option-1-Automatic-push-notification-handling","role":"pseudoSymbol"},"doc://Braze/tutorials/Braze/c2-contentcardsui#Optional-Content-Cards-customization":{"kind":"section","type":"section","abstract":[{"text":"Learn how to display ","type":"text"},{"identifier":"https:\/\/www.braze.com\/docs\/user_guide\/message_building_by_channel\/content_cards\/","isActive":true,"type":"reference"},{"text":" to your users using the Braze provided user interface.","type":"text"}],"url":"\/tutorials\/braze\/c2-contentcardsui#Optional-Content-Cards-customization","role":"pseudoSymbol","identifier":"doc:\/\/Braze\/tutorials\/Braze\/c2-contentcardsui#Optional-Content-Cards-customization","title":"Optional: Content Cards customization"},"doc://Braze/tutorials/Braze/b4-live-activities#Tracking-your-Live-Activity-with-Braze":{"title":"Tracking your Live Activity with Braze","abstract":[{"type":"text","text":"Learn how to remotely track and manage your iOS "},{"type":"reference","identifier":"https:\/\/developer.apple.com\/documentation\/activitykit\/updating-and-ending-your-live-activity-with-activitykit-push-notifications","isActive":true},{"type":"text","text":" with Braze push notifications."}],"kind":"section","identifier":"doc:\/\/Braze\/tutorials\/Braze\/b4-live-activities#Tracking-your-Live-Activity-with-Braze","role":"pseudoSymbol","type":"section","url":"\/tutorials\/braze\/b4-live-activities#Tracking-your-Live-Activity-with-Braze"},"doc://Braze/tutorials/Braze/a1-installation#Braze-Swift-Package":{"kind":"section","type":"section","title":"Braze Swift Package","url":"\/tutorials\/braze\/a1-installation#Braze-Swift-Package","identifier":"doc:\/\/Braze\/tutorials\/Braze\/a1-installation#Braze-Swift-Package","role":"pseudoSymbol","abstract":[{"type":"text","text":"Install the SDK using the Swift Package Manager."}]},"doc://Braze/tutorials/Braze/c2-contentcardsui#BrazeContentCardsUI":{"title":"BrazeContentCardsUI","abstract":[{"text":"Learn how to display ","type":"text"},{"isActive":true,"identifier":"https:\/\/www.braze.com\/docs\/user_guide\/message_building_by_channel\/content_cards\/","type":"reference"},{"text":" to your users using the Braze provided user interface.","type":"text"}],"kind":"section","identifier":"doc:\/\/Braze\/tutorials\/Braze\/c2-contentcardsui#BrazeContentCardsUI","type":"section","url":"\/tutorials\/braze\/c2-contentcardsui#BrazeContentCardsUI","role":"pseudoSymbol"},"doc://Braze/tutorials/Braze/a1-installation":{"role":"project","estimatedTime":"5min","identifier":"doc:\/\/Braze\/tutorials\/Braze\/a1-installation","url":"\/tutorials\/braze\/a1-installation","type":"topic","abstract":[{"text":"Install the SDK using the Swift Package Manager.","type":"text"}],"title":"Installation","kind":"project"},"doc://Braze/tutorials/Braze/c2-contentcardsui#Optional-Content-Cards-view-controller-Delegate":{"identifier":"doc:\/\/Braze\/tutorials\/Braze\/c2-contentcardsui#Optional-Content-Cards-view-controller-Delegate","role":"pseudoSymbol","url":"\/tutorials\/braze\/c2-contentcardsui#Optional-Content-Cards-view-controller-Delegate","kind":"section","title":"Optional: Content Cards view controller Delegate","type":"section","abstract":[{"type":"text","text":"Learn how to display "},{"identifier":"https:\/\/www.braze.com\/docs\/user_guide\/message_building_by_channel\/content_cards\/","type":"reference","isActive":true},{"type":"text","text":" to your users using the Braze provided user interface."}]},"doc://Braze/tutorials/Braze/a3-analytics#Log-custom-events":{"abstract":[{"text":"Learn how to log user attributes, custom events, purchases.","type":"text"}],"role":"pseudoSymbol","kind":"section","url":"\/tutorials\/braze\/a3-analytics#Log-custom-events","type":"section","title":"Log custom events","identifier":"doc:\/\/Braze\/tutorials\/Braze\/a3-analytics#Log-custom-events"},"doc://Braze/tutorials/00-integration-path/User-Interface":{"identifier":"doc:\/\/Braze\/tutorials\/00-integration-path\/User-Interface","kind":"article","type":"topic","url":"\/tutorials\/00-integration-path\/user-interface","role":"article","title":"User Interface","abstract":[]},"doc://Braze/tutorials/Braze/c4-bannersui":{"url":"\/tutorials\/braze\/c4-bannersui","identifier":"doc:\/\/Braze\/tutorials\/Braze\/c4-bannersui","abstract":[{"type":"text","text":"Learn how to display Banners to your users using the Braze provided user interface. This example showcases how to add Banners to your app using either UIKit (Option 1) or SwiftUI (Option 2)."}],"role":"project","title":"Banners UI","type":"topic","kind":"project","estimatedTime":"10min"},"doc://Braze/tutorials/Braze/c1-inappmessageui":{"role":"project","estimatedTime":"10min","title":"In-App Message UI","url":"\/tutorials\/braze\/c1-inappmessageui","abstract":[{"text":"Learn how to display ","type":"text"},{"isActive":true,"type":"reference","identifier":"https:\/\/www.braze.com\/docs\/user_guide\/message_building_by_channel\/in-app_messages"},{"text":" to your users using the Braze provided user interface.","type":"text"}],"identifier":"doc:\/\/Braze\/tutorials\/Braze\/c1-inappmessageui","type":"topic","kind":"project"},"doc://Braze/tutorials/00-integration-path/Location":{"title":"Location","abstract":[],"url":"\/tutorials\/00-integration-path\/location","role":"article","kind":"article","identifier":"doc:\/\/Braze\/tutorials\/00-integration-path\/Location","type":"topic"},"b4-07.swift":{"fileType":"swift","syntax":"swift","fileName":"AppDelegate.swift","content":["import UIKit","import BrazeKit","","#if canImport(ActivityKit)","  import ActivityKit","#endif","","@main","class AppDelegate: UIResponder, UIApplicationDelegate {","","  static var braze: Braze? = nil","","  func application(","    _ application: UIApplication,","    didFinishLaunchingWithOptions launchOptions: [UIApplication.LaunchOptionsKey: Any]?","  ) -> Bool {","    ","    if #available(iOS 16.1, *) {","      Self.braze?.liveActivities.resumeActivities(","        ofType: Activity<BasketballActivityAttributes>.self","      )","    }","","    return true","  }","}"],"highlights":[],"identifier":"b4-07.swift","type":"file"},"b4-04.swift":{"fileType":"swift","syntax":"swift","fileName":"LiveActivityManager.swift","content":["import BrazeKit","","#if canImport(ActivityKit)","  import ActivityKit","#endif","","class LiveActivityManager {","  ","  @available(iOS 16.2, *)","  func createActivity() {","    let activityAttributes = BasketballActivityAttributes(team1Name: \"Team 1\", team2Name: \"Team 2\")","    let contentState = BasketballActivityAttributes.ContentState(team1Score: 0, team2Score: 0)","    let activityContent = ActivityContent(state: contentState, staleDate: nil)","    \/\/ Ensure that your Live Activity is created with the `pushType` parameter set to `.token`.","    if let activity = try? Activity.request(attributes: activityAttributes,","                                            content: activityContent,","                                            pushType: .token) {","      \/\/ Register your Live Activity with Braze using the tag `live-activity-1`.","      AppDelegate.braze?.liveActivities.launchActivity(pushTokenTag: \"live-activity-1\",","                                                       activity: activity)","    }","  }","  ","}"],"highlights":[],"identifier":"b4-04.swift","type":"file"},"https://www.braze.com/docs/user_guide/message_building_by_channel/content_cards/":{"identifier":"https:\/\/www.braze.com\/docs\/user_guide\/message_building_by_channel\/content_cards\/","title":"Content Cards","titleInlineContent":[{"text":"Content Cards","type":"text"}],"type":"link","url":"https:\/\/www.braze.com\/docs\/user_guide\/message_building_by_channel\/content_cards\/"},"b4-02.swift":{"fileType":"swift","syntax":"swift","fileName":"LiveActivityManager.swift","content":["class LiveActivityManager {","  ","  func createActivity() {","    ","  }","  ","}"],"highlights":[],"identifier":"b4-02.swift","type":"file"},"https://developer.apple.com/documentation/activitykit/updating-and-ending-your-live-activity-with-activitykit-push-notifications":{"identifier":"https:\/\/developer.apple.com\/documentation\/activitykit\/updating-and-ending-your-live-activity-with-activitykit-push-notifications","title":"Live Activities","titleInlineContent":[{"text":"Live Activities","type":"text"}],"type":"link","url":"https:\/\/developer.apple.com\/documentation\/activitykit\/updating-and-ending-your-live-activity-with-activitykit-push-notifications"},"https://developer.apple.com/documentation/activitykit/activity":{"titleInlineContent":[{"type":"codeVoice","code":"Activity"}],"url":"https:\/\/developer.apple.com\/documentation\/activitykit\/activity","identifier":"https:\/\/developer.apple.com\/documentation\/activitykit\/activity","type":"link","title":"Activity"},"doc://Braze/tutorials/Braze/d1-brazelocation#BrazeLocationProvider":{"url":"\/tutorials\/braze\/d1-brazelocation#BrazeLocationProvider","role":"pseudoSymbol","type":"section","title":"BrazeLocationProvider","abstract":[{"text":"Learn how to implement ","type":"text"},{"identifier":"https:\/\/www.braze.com\/docs\/user_guide\/engagement_tools\/locations_and_geofences\/","type":"reference","isActive":true},{"text":" using the ","type":"text"},{"type":"strong","inlineContent":[{"type":"text","text":"BrazeLocation"}]},{"text":" module.","type":"text"}],"identifier":"doc:\/\/Braze\/tutorials\/Braze\/d1-brazelocation#BrazeLocationProvider","kind":"section"},"https://www.braze.com/docs/user_guide/message_building_by_channel/push/advanced_push_options/push_stories/":{"titleInlineContent":[{"text":"Push Story","type":"text"}],"url":"https:\/\/www.braze.com\/docs\/user_guide\/message_building_by_channel\/push\/advanced_push_options\/push_stories\/","identifier":"https:\/\/www.braze.com\/docs\/user_guide\/message_building_by_channel\/push\/advanced_push_options\/push_stories\/","type":"link","title":"Push Story"},"doc://Braze/tutorials/Braze/b2-rich-push-notifications#Notification-Service-Extension":{"title":"Notification Service Extension","type":"section","abstract":[{"text":"Learn how to support receiving rich push notifications with images, audio and video.","type":"text"}],"kind":"section","url":"\/tutorials\/braze\/b2-rich-push-notifications#Notification-Service-Extension","identifier":"doc:\/\/Braze\/tutorials\/Braze\/b2-rich-push-notifications#Notification-Service-Extension","role":"pseudoSymbol"},"doc://Braze/tutorials/Braze/b4-live-activities#Creating-a-Live-Activity":{"abstract":[{"text":"Learn how to remotely track and manage your iOS ","type":"text"},{"type":"reference","identifier":"https:\/\/developer.apple.com\/documentation\/activitykit\/updating-and-ending-your-live-activity-with-activitykit-push-notifications","isActive":true},{"text":" with Braze push notifications.","type":"text"}],"kind":"section","title":"Creating a Live Activity","identifier":"doc:\/\/Braze\/tutorials\/Braze\/b4-live-activities#Creating-a-Live-Activity","url":"\/tutorials\/braze\/b4-live-activities#Creating-a-Live-Activity","type":"section","role":"pseudoSymbol"},"doc://Braze/tutorials/Braze/e1-privacy-tracking#Respond-to-App-Tracking-Transparency-permissions":{"kind":"section","identifier":"doc:\/\/Braze\/tutorials\/Braze\/e1-privacy-tracking#Respond-to-App-Tracking-Transparency-permissions","url":"\/tutorials\/braze\/e1-privacy-tracking#Respond-to-App-Tracking-Transparency-permissions","title":"Respond to App Tracking Transparency permissions","type":"section","abstract":[{"type":"text","text":"Learn how to manage your data collection practices for tracking."}],"role":"pseudoSymbol"},"doc://Braze/tutorials/Braze/b4-live-activities#Resuming-Live-Activity-tracking":{"identifier":"doc:\/\/Braze\/tutorials\/Braze\/b4-live-activities#Resuming-Live-Activity-tracking","title":"Resuming Live Activity tracking","abstract":[{"type":"text","text":"Learn how to remotely track and manage your iOS "},{"isActive":true,"identifier":"https:\/\/developer.apple.com\/documentation\/activitykit\/updating-and-ending-your-live-activity-with-activitykit-push-notifications","type":"reference"},{"type":"text","text":" with Braze push notifications."}],"role":"pseudoSymbol","url":"\/tutorials\/braze\/b4-live-activities#Resuming-Live-Activity-tracking","type":"section","kind":"section"},"https://www.braze.com/docs/user_guide/engagement_tools/locations_and_geofences/":{"url":"https:\/\/www.braze.com\/docs\/user_guide\/engagement_tools\/locations_and_geofences\/","title":"location analytics and geofence monitoring","type":"link","titleInlineContent":[{"type":"text","text":"location analytics and geofence monitoring"}],"identifier":"https:\/\/www.braze.com\/docs\/user_guide\/engagement_tools\/locations_and_geofences\/"},"b4-14.swift":{"identifier":"b4-14.swift","type":"file","fileName":"LiveActivityManager.swift","syntax":"swift","content":["class LiveActivityManager {","  ","  func optOutOfBasketball() {","    AppDelegate.braze?.liveActivities.optOutPushToStart(type: \"BasketballActivityAttributes\")","  }","  ","}"],"fileType":"swift","highlights":[]}}}