{"variants":[{"traits":[{"interfaceLanguage":"swift"}],"paths":["\/tutorials\/braze\/c3-gif-support"]}],"schemaVersion":{"major":0,"minor":3,"patch":0},"sections":[{"estimatedTimeInMinutes":5,"chapter":"User Interface","title":"GIF Support","kind":"hero","content":[{"inlineContent":[{"text":"Learn how to add GIF images support to Braze provided user interface using third party libraries.","type":"text"}],"type":"paragraph"}]},{"tasks":[{"stepsSection":[{"code":null,"type":"step","content":[{"type":"paragraph","inlineContent":[{"text":"Follow the installation directions in the ","type":"text"},{"type":"reference","isActive":true,"identifier":"https:\/\/github.com\/SDWebImage\/SDWebImage"},{"text":" repository to add it to your Xcode project.","type":"text"}]}],"media":null,"caption":[],"runtimePreview":null},{"code":"c3-a-01.swift","type":"step","content":[{"type":"paragraph","inlineContent":[{"text":"Create a new file ","type":"text"},{"inlineContent":[{"text":"SDWebImageGIFViewProvider.swift","type":"text"}],"type":"strong"},{"text":".","type":"text"}]}],"media":null,"caption":[],"runtimePreview":null},{"code":"c3-a-02.swift","type":"step","content":[{"inlineContent":[{"type":"text","text":"Import the "},{"type":"strong","inlineContent":[{"type":"text","text":"BrazeUI"}]},{"type":"text","text":" and "},{"type":"strong","inlineContent":[{"type":"text","text":"SDWebImage"}]},{"type":"text","text":" packages at the top of the file."}],"type":"paragraph"}],"media":null,"caption":[],"runtimePreview":null},{"code":"c3-a-03.swift","type":"step","content":[{"inlineContent":[{"text":"Copy and paste the ","type":"text"},{"inlineContent":[{"type":"text","text":"SDWebImage"}],"type":"strong"},{"text":" sample ","type":"text"},{"identifier":"doc:\/\/Braze\/documentation\/BrazeUI\/GIFViewProvider","isActive":true,"type":"reference"},{"text":" from ","type":"text"},{"identifier":"doc:\/\/Braze\/documentation\/Braze\/gif-support-integrations","isActive":true,"type":"reference"},{"text":".","type":"text"}],"type":"paragraph"}],"media":null,"caption":[],"runtimePreview":null},{"code":"c3-a-04.swift","type":"step","content":[{"inlineContent":[{"type":"text","text":"Open your application "},{"type":"strong","inlineContent":[{"type":"text","text":"AppDelegate.swift"}]},{"type":"text","text":" file."}],"type":"paragraph"}],"media":null,"caption":[],"runtimePreview":null},{"code":"c3-a-05.swift","type":"step","content":[{"type":"paragraph","inlineContent":[{"type":"text","text":"Add GIF support to the "},{"type":"strong","inlineContent":[{"text":"BrazeUI","type":"text"}]},{"type":"text","text":" components using the "},{"type":"strong","inlineContent":[{"text":"SDWebImage","type":"text"}]},{"type":"text","text":" "},{"type":"strong","inlineContent":[{"type":"text","text":"GIFViewProvider"}]},{"type":"text","text":"."}]}],"media":null,"caption":[],"runtimePreview":null}],"contentSection":[{"kind":"contentAndMedia","content":[{"type":"paragraph","inlineContent":[{"type":"text","text":"Create a "},{"type":"reference","identifier":"doc:\/\/Braze\/documentation\/BrazeUI\/GIFViewProvider","isActive":true},{"type":"text","text":" to let the Braze UI use your own or any third party GIF supporting "},{"type":"codeVoice","code":"UIView"},{"type":"text","text":"."}]},{"type":"paragraph","inlineContent":[{"type":"text","text":"This tutorial shows how to use "},{"type":"reference","isActive":true,"identifier":"https:\/\/github.com\/SDWebImage\/SDWebImage"},{"type":"text","text":" to add GIF support. Sample implementations are available in "},{"type":"reference","isActive":true,"identifier":"doc:\/\/Braze\/documentation\/Braze\/gif-support-integrations"},{"type":"text","text":"."}]}],"mediaPosition":"trailing"}],"title":"Adding GIF support with SDWebImage","anchor":"Adding-GIF-support-with-SDWebImage"}],"kind":"tasks"},{"action":{"identifier":"doc:\/\/Braze\/tutorials\/Braze\/d1-brazelocation","type":"reference","isActive":true,"overridingTitle":"Get started","overridingTitleInlineContent":[{"type":"text","text":"Get started"}]},"featuredEyebrow":"Tutorial","title":"Locations and Geofences","abstract":[{"type":"text","text":"Learn how to implement "},{"identifier":"https:\/\/www.braze.com\/docs\/user_guide\/engagement_tools\/locations_and_geofences\/","type":"reference","isActive":true},{"type":"text","text":" using the "},{"type":"strong","inlineContent":[{"type":"text","text":"BrazeLocation"}]},{"type":"text","text":" module."}],"kind":"callToAction"}],"identifier":{"url":"doc:\/\/Braze\/tutorials\/Braze\/c3-gif-support","interfaceLanguage":"swift"},"kind":"project","hierarchy":{"modules":[{"reference":"doc:\/\/Braze\/tutorials\/00-integration-path\/Braze-Essentials","projects":[{"reference":"doc:\/\/Braze\/tutorials\/Braze\/a1-installation","sections":[{"kind":"task","reference":"doc:\/\/Braze\/tutorials\/Braze\/a1-installation#Braze-Swift-Package"}]},{"reference":"doc:\/\/Braze\/tutorials\/Braze\/a2-configure-braze","sections":[{"reference":"doc:\/\/Braze\/tutorials\/Braze\/a2-configure-braze#The-Braze-instance","kind":"task"}]},{"reference":"doc:\/\/Braze\/tutorials\/Braze\/a3-analytics","sections":[{"kind":"task","reference":"doc:\/\/Braze\/tutorials\/Braze\/a3-analytics#Identify-the-current-user"},{"kind":"task","reference":"doc:\/\/Braze\/tutorials\/Braze\/a3-analytics#Log-custom-events"},{"kind":"task","reference":"doc:\/\/Braze\/tutorials\/Braze\/a3-analytics#Log-purchases"}]}]},{"reference":"doc:\/\/Braze\/tutorials\/00-integration-path\/Push-Notifications","projects":[{"sections":[{"kind":"task","reference":"doc:\/\/Braze\/tutorials\/Braze\/b1-standard-push-notifications#Setup-your-Xcode-project"},{"kind":"task","reference":"doc:\/\/Braze\/tutorials\/Braze\/b1-standard-push-notifications#Option-1-Automatic-push-notification-handling"},{"kind":"task","reference":"doc:\/\/Braze\/tutorials\/Braze\/b1-standard-push-notifications#Option-2-Implement-the-push-notification-handlers-manually"}],"reference":"doc:\/\/Braze\/tutorials\/Braze\/b1-standard-push-notifications"},{"sections":[{"reference":"doc:\/\/Braze\/tutorials\/Braze\/b2-rich-push-notifications#Notification-Service-Extension","kind":"task"}],"reference":"doc:\/\/Braze\/tutorials\/Braze\/b2-rich-push-notifications"},{"sections":[{"kind":"task","reference":"doc:\/\/Braze\/tutorials\/Braze\/b3-push-stories#Notification-Content-Extension"}],"reference":"doc:\/\/Braze\/tutorials\/Braze\/b3-push-stories"},{"sections":[{"kind":"task","reference":"doc:\/\/Braze\/tutorials\/Braze\/b4-live-activities#Creating-a-Live-Activity"},{"kind":"task","reference":"doc:\/\/Braze\/tutorials\/Braze\/b4-live-activities#Tracking-your-Live-Activity-with-Braze"},{"kind":"task","reference":"doc:\/\/Braze\/tutorials\/Braze\/b4-live-activities#Resuming-Live-Activity-tracking"},{"kind":"task","reference":"doc:\/\/Braze\/tutorials\/Braze\/b4-live-activities#Setting-up-push-to-start"},{"kind":"task","reference":"doc:\/\/Braze\/tutorials\/Braze\/b4-live-activities#Opting-out-of-push-to-start"}],"reference":"doc:\/\/Braze\/tutorials\/Braze\/b4-live-activities"}]},{"reference":"doc:\/\/Braze\/tutorials\/00-integration-path\/User-Interface","projects":[{"reference":"doc:\/\/Braze\/tutorials\/Braze\/c1-inappmessageui","sections":[{"kind":"task","reference":"doc:\/\/Braze\/tutorials\/Braze\/c1-inappmessageui#BrazeInAppMessageUI"},{"kind":"task","reference":"doc:\/\/Braze\/tutorials\/Braze\/c1-inappmessageui#Optional-In-App-Message-UI-Delegate"}]},{"reference":"doc:\/\/Braze\/tutorials\/Braze\/c2-contentcardsui","sections":[{"kind":"task","reference":"doc:\/\/Braze\/tutorials\/Braze\/c2-contentcardsui#BrazeContentCardsUI"},{"kind":"task","reference":"doc:\/\/Braze\/tutorials\/Braze\/c2-contentcardsui#Optional-Content-Cards-customization"},{"kind":"task","reference":"doc:\/\/Braze\/tutorials\/Braze\/c2-contentcardsui#Optional-Content-Cards-view-controller-Delegate"}]},{"reference":"doc:\/\/Braze\/tutorials\/Braze\/c4-bannersui","sections":[{"reference":"doc:\/\/Braze\/tutorials\/Braze\/c4-bannersui#Option-1-BrazeBannersUI-in-UIKit","kind":"task"},{"reference":"doc:\/\/Braze\/tutorials\/Braze\/c4-bannersui#Option-2-BrazeBannersUI-in-SwiftUI","kind":"task"}]},{"reference":"doc:\/\/Braze\/tutorials\/Braze\/c3-gif-support","sections":[{"reference":"doc:\/\/Braze\/tutorials\/Braze\/c3-gif-support#Adding-GIF-support-with-SDWebImage","kind":"task"}]}]},{"reference":"doc:\/\/Braze\/tutorials\/00-integration-path\/Location","projects":[{"reference":"doc:\/\/Braze\/tutorials\/Braze\/d1-brazelocation","sections":[{"reference":"doc:\/\/Braze\/tutorials\/Braze\/d1-brazelocation#Setup-your-Xcode-project","kind":"task"},{"reference":"doc:\/\/Braze\/tutorials\/Braze\/d1-brazelocation#BrazeLocationProvider","kind":"task"}]}]},{"reference":"doc:\/\/Braze\/tutorials\/00-integration-path\/Privacy-Tracking","projects":[{"sections":[{"reference":"doc:\/\/Braze\/tutorials\/Braze\/e1-privacy-tracking#Prepare-your-app-for-App-Tracking-Transparency","kind":"task"},{"reference":"doc:\/\/Braze\/tutorials\/Braze\/e1-privacy-tracking#Configure-your-tracking-data","kind":"task"},{"reference":"doc:\/\/Braze\/tutorials\/Braze\/e1-privacy-tracking#Respond-to-App-Tracking-Transparency-permissions","kind":"task"},{"reference":"doc:\/\/Braze\/tutorials\/Braze\/e1-privacy-tracking#Updating-your-tracking-configurations-at-runtime","kind":"task"}],"reference":"doc:\/\/Braze\/tutorials\/Braze\/e1-privacy-tracking"}]}],"reference":"doc:\/\/Braze\/tutorials\/00-integration-path","paths":[["doc:\/\/Braze\/tutorials\/00-integration-path","doc:\/\/Braze\/tutorials\/00-integration-path\/$volume","doc:\/\/Braze\/tutorials\/00-integration-path\/User-Interface"],["doc:\/\/Braze\/documentation\/BrazeKit"],["doc:\/\/Braze\/documentation\/BrazeUI"]]},"metadata":{"categoryPathComponent":"00-integration-path","title":"GIF Support","category":"Braze","role":"project"},"references":{"doc://Braze/tutorials/Braze/c1-inappmessageui#BrazeInAppMessageUI":{"type":"section","title":"BrazeInAppMessageUI","role":"pseudoSymbol","identifier":"doc:\/\/Braze\/tutorials\/Braze\/c1-inappmessageui#BrazeInAppMessageUI","kind":"section","abstract":[{"type":"text","text":"Learn how to display "},{"type":"reference","identifier":"https:\/\/www.braze.com\/docs\/user_guide\/message_building_by_channel\/in-app_messages","isActive":true},{"type":"text","text":" to your users using the Braze provided user interface."}],"url":"\/tutorials\/braze\/c1-inappmessageui#BrazeInAppMessageUI"},"doc://Braze/tutorials/Braze/d1-brazelocation#Setup-your-Xcode-project":{"abstract":[{"type":"text","text":"Learn how to implement "},{"type":"reference","identifier":"https:\/\/www.braze.com\/docs\/user_guide\/engagement_tools\/locations_and_geofences\/","isActive":true},{"type":"text","text":" using the "},{"type":"strong","inlineContent":[{"text":"BrazeLocation","type":"text"}]},{"type":"text","text":" module."}],"kind":"section","identifier":"doc:\/\/Braze\/tutorials\/Braze\/d1-brazelocation#Setup-your-Xcode-project","role":"pseudoSymbol","title":"Setup your Xcode project","url":"\/tutorials\/braze\/d1-brazelocation#Setup-your-Xcode-project","type":"section"},"doc://Braze/tutorials/Braze/c2-contentcardsui#Optional-Content-Cards-view-controller-Delegate":{"title":"Optional: Content Cards view controller Delegate","role":"pseudoSymbol","url":"\/tutorials\/braze\/c2-contentcardsui#Optional-Content-Cards-view-controller-Delegate","identifier":"doc:\/\/Braze\/tutorials\/Braze\/c2-contentcardsui#Optional-Content-Cards-view-controller-Delegate","abstract":[{"text":"Learn how to display ","type":"text"},{"identifier":"https:\/\/www.braze.com\/docs\/user_guide\/message_building_by_channel\/content_cards\/","isActive":true,"type":"reference"},{"text":" to your users using the Braze provided user interface.","type":"text"}],"kind":"section","type":"section"},"doc://Braze/tutorials/Braze/b3-push-stories#Notification-Content-Extension":{"identifier":"doc:\/\/Braze\/tutorials\/Braze\/b3-push-stories#Notification-Content-Extension","abstract":[{"type":"text","text":"Learn how to support receiving "},{"type":"reference","isActive":true,"identifier":"https:\/\/www.braze.com\/docs\/user_guide\/message_building_by_channel\/push\/advanced_push_options\/push_stories\/"},{"type":"text","text":" notifications."}],"kind":"section","type":"section","title":"Notification Content Extension","role":"pseudoSymbol","url":"\/tutorials\/braze\/b3-push-stories#Notification-Content-Extension"},"doc://Braze/tutorials/Braze/a2-configure-braze#The-Braze-instance":{"abstract":[{"type":"text","text":"Create and configure the Braze instance."}],"title":"The Braze instance","type":"section","url":"\/tutorials\/braze\/a2-configure-braze#The-Braze-instance","role":"pseudoSymbol","identifier":"doc:\/\/Braze\/tutorials\/Braze\/a2-configure-braze#The-Braze-instance","kind":"section"},"doc://Braze/tutorials/Braze/b3-push-stories":{"kind":"project","role":"project","estimatedTime":"20min","identifier":"doc:\/\/Braze\/tutorials\/Braze\/b3-push-stories","title":"Push Stories","type":"topic","url":"\/tutorials\/braze\/b3-push-stories","abstract":[{"text":"Learn how to support receiving ","type":"text"},{"isActive":true,"identifier":"https:\/\/www.braze.com\/docs\/user_guide\/message_building_by_channel\/push\/advanced_push_options\/push_stories\/","type":"reference"},{"text":" notifications.","type":"text"}]},"c3-a-01.swift":{"fileName":"SDWebImageGIFViewProvider.swift","type":"file","content":["import UIKit"],"fileType":"swift","highlights":[],"identifier":"c3-a-01.swift","syntax":"swift"},"doc://Braze/tutorials/Braze/e1-privacy-tracking#Updating-your-tracking-configurations-at-runtime":{"type":"section","title":"Updating your tracking configurations at runtime","url":"\/tutorials\/braze\/e1-privacy-tracking#Updating-your-tracking-configurations-at-runtime","identifier":"doc:\/\/Braze\/tutorials\/Braze\/e1-privacy-tracking#Updating-your-tracking-configurations-at-runtime","abstract":[{"type":"text","text":"Learn how to manage your data collection practices for tracking."}],"role":"pseudoSymbol","kind":"section"},"doc://Braze/tutorials/Braze/b4-live-activities#Opting-out-of-push-to-start":{"identifier":"doc:\/\/Braze\/tutorials\/Braze\/b4-live-activities#Opting-out-of-push-to-start","role":"pseudoSymbol","kind":"section","url":"\/tutorials\/braze\/b4-live-activities#Opting-out-of-push-to-start","abstract":[{"text":"Learn how to remotely track and manage your iOS ","type":"text"},{"identifier":"https:\/\/developer.apple.com\/documentation\/activitykit\/updating-and-ending-your-live-activity-with-activitykit-push-notifications","isActive":true,"type":"reference"},{"text":" with Braze push notifications.","type":"text"}],"title":"Opting out of push-to-start","type":"section"},"doc://Braze/tutorials/Braze/e1-privacy-tracking":{"url":"\/tutorials\/braze\/e1-privacy-tracking","identifier":"doc:\/\/Braze\/tutorials\/Braze\/e1-privacy-tracking","type":"topic","abstract":[{"text":"Learn how to manage your data collection practices for tracking.","type":"text"}],"estimatedTime":"10min","title":"Privacy Tracking Data","kind":"project","role":"project"},"doc://Braze/tutorials/Braze/d1-brazelocation":{"estimatedTime":"10min","kind":"project","url":"\/tutorials\/braze\/d1-brazelocation","identifier":"doc:\/\/Braze\/tutorials\/Braze\/d1-brazelocation","role":"project","type":"topic","abstract":[{"text":"Learn how to implement ","type":"text"},{"isActive":true,"identifier":"https:\/\/www.braze.com\/docs\/user_guide\/engagement_tools\/locations_and_geofences\/","type":"reference"},{"text":" using the ","type":"text"},{"inlineContent":[{"type":"text","text":"BrazeLocation"}],"type":"strong"},{"text":" module.","type":"text"}],"title":"Locations and Geofences"},"c3-a-04.swift":{"highlights":[],"content":["import UIKit","import BrazeKit","import BrazeUI","","@main","class AppDelegate: UIResponder, UIApplicationDelegate {","","  static var braze: Braze? = nil","","  func application(","    _ application: UIApplication,","    didFinishLaunchingWithOptions launchOptions: [UIApplication.LaunchOptionsKey: Any]?","  ) -> Bool {","    \/* ... *\/","","    return true","  }","}"],"fileName":"AppDelegate.swift","fileType":"swift","syntax":"swift","type":"file","identifier":"c3-a-04.swift"},"doc://Braze/tutorials/Braze/e1-privacy-tracking#Respond-to-App-Tracking-Transparency-permissions":{"url":"\/tutorials\/braze\/e1-privacy-tracking#Respond-to-App-Tracking-Transparency-permissions","role":"pseudoSymbol","type":"section","kind":"section","abstract":[{"type":"text","text":"Learn how to manage your data collection practices for tracking."}],"identifier":"doc:\/\/Braze\/tutorials\/Braze\/e1-privacy-tracking#Respond-to-App-Tracking-Transparency-permissions","title":"Respond to App Tracking Transparency permissions"},"c3-a-02.swift":{"fileName":"SDWebImageGIFViewProvider.swift","type":"file","content":["import UIKit","import BrazeUI","import SDWebImage"],"fileType":"swift","highlights":[],"identifier":"c3-a-02.swift","syntax":"swift"},"doc://Braze/tutorials/Braze/b4-live-activities#Tracking-your-Live-Activity-with-Braze":{"kind":"section","abstract":[{"type":"text","text":"Learn how to remotely track and manage your iOS "},{"identifier":"https:\/\/developer.apple.com\/documentation\/activitykit\/updating-and-ending-your-live-activity-with-activitykit-push-notifications","type":"reference","isActive":true},{"type":"text","text":" with Braze push notifications."}],"title":"Tracking your Live Activity with Braze","type":"section","identifier":"doc:\/\/Braze\/tutorials\/Braze\/b4-live-activities#Tracking-your-Live-Activity-with-Braze","role":"pseudoSymbol","url":"\/tutorials\/braze\/b4-live-activities#Tracking-your-Live-Activity-with-Braze"},"doc://Braze/tutorials/Braze/a2-configure-braze":{"type":"topic","title":"Configure Braze","role":"project","abstract":[{"text":"Create and configure the Braze instance.","type":"text"}],"estimatedTime":"5min","identifier":"doc:\/\/Braze\/tutorials\/Braze\/a2-configure-braze","kind":"project","url":"\/tutorials\/braze\/a2-configure-braze"},"doc://Braze/tutorials/Braze/b2-rich-push-notifications":{"estimatedTime":"5min","title":"Rich Push Notifications","kind":"project","identifier":"doc:\/\/Braze\/tutorials\/Braze\/b2-rich-push-notifications","abstract":[{"text":"Learn how to support receiving rich push notifications with images, audio and video.","type":"text"}],"role":"project","url":"\/tutorials\/braze\/b2-rich-push-notifications","type":"topic"},"doc://Braze/tutorials/Braze/c4-bannersui#Option-1-BrazeBannersUI-in-UIKit":{"title":"Option 1: BrazeBannersUI in UIKit","abstract":[{"type":"text","text":"Learn how to display Banners to your users using the Braze provided user interface. This example showcases how to add Banners to your app using either UIKit (Option 1) or SwiftUI (Option 2)."}],"type":"section","role":"pseudoSymbol","url":"\/tutorials\/braze\/c4-bannersui#Option-1-BrazeBannersUI-in-UIKit","kind":"section","identifier":"doc:\/\/Braze\/tutorials\/Braze\/c4-bannersui#Option-1-BrazeBannersUI-in-UIKit"},"c3-a-03.swift":{"fileType":"swift","identifier":"c3-a-03.swift","fileName":"SDWebImageGIFViewProvider.swift","syntax":"swift","highlights":[],"type":"file","content":["import UIKit","import BrazeUI","import SDWebImage","","extension GIFViewProvider {","","  \/\/\/ A GIF view provider using [SDWebImage](https:\/\/github.com\/SDWebImage\/SDWebImage) as a","  \/\/\/ rendering library.","  public static let sdWebImage = Self(","    view: { SDAnimatedImageView(image: image(for: $0)) },","    updateView: { ($0 as? SDAnimatedImageView)?.image = image(for: $1) }","  )","","  private static func image(for url: URL?) -> UIImage? {","    guard let url else { return nil }","    return url.pathExtension == \"gif\"","      ? SDAnimatedImage(contentsOfFile: url.path)","      : UIImage(contentsOfFile: url.path)","  }","","}"]},"doc://Braze/tutorials/Braze/c4-bannersui":{"estimatedTime":"10min","title":"Banners UI","type":"topic","url":"\/tutorials\/braze\/c4-bannersui","abstract":[{"text":"Learn how to display Banners to your users using the Braze provided user interface. This example showcases how to add Banners to your app using either UIKit (Option 1) or SwiftUI (Option 2).","type":"text"}],"kind":"project","role":"project","identifier":"doc:\/\/Braze\/tutorials\/Braze\/c4-bannersui"},"doc://Braze/tutorials/Braze/e1-privacy-tracking#Configure-your-tracking-data":{"title":"Configure your tracking data","role":"pseudoSymbol","type":"section","url":"\/tutorials\/braze\/e1-privacy-tracking#Configure-your-tracking-data","abstract":[{"text":"Learn how to manage your data collection practices for tracking.","type":"text"}],"kind":"section","identifier":"doc:\/\/Braze\/tutorials\/Braze\/e1-privacy-tracking#Configure-your-tracking-data"},"doc://Braze/tutorials/Braze/c1-inappmessageui#Optional-In-App-Message-UI-Delegate":{"kind":"section","type":"section","abstract":[{"text":"Learn how to display ","type":"text"},{"identifier":"https:\/\/www.braze.com\/docs\/user_guide\/message_building_by_channel\/in-app_messages","isActive":true,"type":"reference"},{"text":" to your users using the Braze provided user interface.","type":"text"}],"identifier":"doc:\/\/Braze\/tutorials\/Braze\/c1-inappmessageui#Optional-In-App-Message-UI-Delegate","url":"\/tutorials\/braze\/c1-inappmessageui#Optional-In-App-Message-UI-Delegate","title":"Optional: In-App Message UI Delegate","role":"pseudoSymbol"},"c3-a-05.swift":{"content":["import UIKit","import BrazeKit","import BrazeUI","","@main","class AppDelegate: UIResponder, UIApplicationDelegate {","","  static var braze: Braze? = nil","","  func application(","    _ application: UIApplication,","    didFinishLaunchingWithOptions launchOptions: [UIApplication.LaunchOptionsKey: Any]?","  ) -> Bool {","    \/* ... *\/","","    GIFViewProvider.shared = .sdWebImage","","    return true","  }","}"],"type":"file","syntax":"swift","fileName":"AppDelegate.swift","highlights":[],"fileType":"swift","identifier":"c3-a-05.swift"},"https://developer.apple.com/documentation/activitykit/updating-and-ending-your-live-activity-with-activitykit-push-notifications":{"titleInlineContent":[{"type":"text","text":"Live Activities"}],"url":"https:\/\/developer.apple.com\/documentation\/activitykit\/updating-and-ending-your-live-activity-with-activitykit-push-notifications","type":"link","title":"Live Activities","identifier":"https:\/\/developer.apple.com\/documentation\/activitykit\/updating-and-ending-your-live-activity-with-activitykit-push-notifications"},"https://www.braze.com/docs/user_guide/message_building_by_channel/push/advanced_push_options/push_stories/":{"url":"https:\/\/www.braze.com\/docs\/user_guide\/message_building_by_channel\/push\/advanced_push_options\/push_stories\/","type":"link","title":"Push Story","identifier":"https:\/\/www.braze.com\/docs\/user_guide\/message_building_by_channel\/push\/advanced_push_options\/push_stories\/","titleInlineContent":[{"text":"Push Story","type":"text"}]},"doc://Braze/tutorials/00-integration-path/User-Interface":{"url":"\/tutorials\/00-integration-path\/user-interface","kind":"article","abstract":[],"identifier":"doc:\/\/Braze\/tutorials\/00-integration-path\/User-Interface","type":"topic","title":"User Interface","role":"article"},"doc://Braze/tutorials/Braze/c1-inappmessageui":{"abstract":[{"text":"Learn how to display ","type":"text"},{"identifier":"https:\/\/www.braze.com\/docs\/user_guide\/message_building_by_channel\/in-app_messages","isActive":true,"type":"reference"},{"text":" to your users using the Braze provided user interface.","type":"text"}],"title":"In-App Message UI","identifier":"doc:\/\/Braze\/tutorials\/Braze\/c1-inappmessageui","kind":"project","url":"\/tutorials\/braze\/c1-inappmessageui","role":"project","estimatedTime":"10min","type":"topic"},"doc://Braze/tutorials/00-integration-path":{"identifier":"doc:\/\/Braze\/tutorials\/00-integration-path","kind":"overview","title":"Integration Path","url":"\/tutorials\/00-integration-path","type":"topic","role":"overview","abstract":[{"text":"Follow these step by step tutorials to learn how to get the most out of the Braze SDK.","type":"text"}]},"https://github.com/SDWebImage/SDWebImage":{"titleInlineContent":[{"text":"SDWebImage","type":"text"}],"url":"https:\/\/github.com\/SDWebImage\/SDWebImage","type":"link","identifier":"https:\/\/github.com\/SDWebImage\/SDWebImage","title":"SDWebImage"},"doc://Braze/tutorials/Braze/a3-analytics#Log-purchases":{"title":"Log purchases","abstract":[{"text":"Learn how to log user attributes, custom events, purchases.","type":"text"}],"url":"\/tutorials\/braze\/a3-analytics#Log-purchases","kind":"section","role":"pseudoSymbol","identifier":"doc:\/\/Braze\/tutorials\/Braze\/a3-analytics#Log-purchases","type":"section"},"doc://Braze/tutorials/Braze/b4-live-activities":{"identifier":"doc:\/\/Braze\/tutorials\/Braze\/b4-live-activities","kind":"project","url":"\/tutorials\/braze\/b4-live-activities","role":"project","estimatedTime":"10min","title":"Live Activities","abstract":[{"type":"text","text":"Learn how to remotely track and manage your iOS "},{"type":"reference","identifier":"https:\/\/developer.apple.com\/documentation\/activitykit\/updating-and-ending-your-live-activity-with-activitykit-push-notifications","isActive":true},{"text":" with Braze push notifications.","type":"text"}],"type":"topic"},"doc://Braze/documentation/BrazeUI/GIFViewProvider":{"navigatorTitle":[{"kind":"identifier","text":"GIFViewProvider"}],"role":"symbol","abstract":[{"type":"text","text":"A type providing methods to create and update views supporting animated GIF images."}],"kind":"symbol","url":"\/documentation\/brazeui\/gifviewprovider","identifier":"doc:\/\/Braze\/documentation\/BrazeUI\/GIFViewProvider","title":"GIFViewProvider","fragments":[{"kind":"keyword","text":"struct"},{"kind":"text","text":" "},{"kind":"identifier","text":"GIFViewProvider"}],"type":"topic"},"doc://Braze/tutorials/Braze/a3-analytics":{"url":"\/tutorials\/braze\/a3-analytics","abstract":[{"type":"text","text":"Learn how to log user attributes, custom events, purchases."}],"title":"Analytics","type":"topic","identifier":"doc:\/\/Braze\/tutorials\/Braze\/a3-analytics","kind":"project","role":"project","estimatedTime":"15min"},"doc://Braze/tutorials/00-integration-path/Privacy-Tracking":{"title":"Privacy Tracking","type":"topic","identifier":"doc:\/\/Braze\/tutorials\/00-integration-path\/Privacy-Tracking","role":"article","url":"\/tutorials\/00-integration-path\/privacy-tracking","kind":"article","abstract":[]},"doc://Braze/tutorials/Braze/c3-gif-support#Adding-GIF-support-with-SDWebImage":{"abstract":[{"text":"Learn how to add GIF images support to Braze provided user interface using third party libraries.","type":"text"}],"url":"\/tutorials\/braze\/c3-gif-support#Adding-GIF-support-with-SDWebImage","type":"section","identifier":"doc:\/\/Braze\/tutorials\/Braze\/c3-gif-support#Adding-GIF-support-with-SDWebImage","title":"Adding GIF support with SDWebImage","role":"pseudoSymbol","kind":"section"},"doc://Braze/tutorials/Braze/e1-privacy-tracking#Prepare-your-app-for-App-Tracking-Transparency":{"identifier":"doc:\/\/Braze\/tutorials\/Braze\/e1-privacy-tracking#Prepare-your-app-for-App-Tracking-Transparency","title":"Prepare your app for App Tracking Transparency","abstract":[{"type":"text","text":"Learn how to manage your data collection practices for tracking."}],"kind":"section","url":"\/tutorials\/braze\/e1-privacy-tracking#Prepare-your-app-for-App-Tracking-Transparency","type":"section","role":"pseudoSymbol"},"doc://Braze/tutorials/Braze/c2-contentcardsui":{"role":"project","identifier":"doc:\/\/Braze\/tutorials\/Braze\/c2-contentcardsui","title":"Content Cards UI","abstract":[{"text":"Learn how to display ","type":"text"},{"identifier":"https:\/\/www.braze.com\/docs\/user_guide\/message_building_by_channel\/content_cards\/","isActive":true,"type":"reference"},{"text":" to your users using the Braze provided user interface.","type":"text"}],"estimatedTime":"10min","kind":"project","type":"topic","url":"\/tutorials\/braze\/c2-contentcardsui"},"doc://Braze/tutorials/Braze/a3-analytics#Log-custom-events":{"identifier":"doc:\/\/Braze\/tutorials\/Braze\/a3-analytics#Log-custom-events","kind":"section","role":"pseudoSymbol","url":"\/tutorials\/braze\/a3-analytics#Log-custom-events","type":"section","abstract":[{"type":"text","text":"Learn how to log user attributes, custom events, purchases."}],"title":"Log custom events"},"doc://Braze/tutorials/Braze/b1-standard-push-notifications#Setup-your-Xcode-project":{"url":"\/tutorials\/braze\/b1-standard-push-notifications#Setup-your-Xcode-project","title":"Setup your Xcode project","kind":"section","identifier":"doc:\/\/Braze\/tutorials\/Braze\/b1-standard-push-notifications#Setup-your-Xcode-project","type":"section","abstract":[{"text":"Learn how to support receiving foreground and background push notifications.","type":"text"}],"role":"pseudoSymbol"},"doc://Braze/tutorials/Braze/c4-bannersui#Option-2-BrazeBannersUI-in-SwiftUI":{"abstract":[{"type":"text","text":"Learn how to display Banners to your users using the Braze provided user interface. This example showcases how to add Banners to your app using either UIKit (Option 1) or SwiftUI (Option 2)."}],"kind":"section","type":"section","title":"Option 2: BrazeBannersUI in SwiftUI","identifier":"doc:\/\/Braze\/tutorials\/Braze\/c4-bannersui#Option-2-BrazeBannersUI-in-SwiftUI","url":"\/tutorials\/braze\/c4-bannersui#Option-2-BrazeBannersUI-in-SwiftUI","role":"pseudoSymbol"},"doc://Braze/tutorials/Braze/c2-contentcardsui#BrazeContentCardsUI":{"abstract":[{"text":"Learn how to display ","type":"text"},{"isActive":true,"type":"reference","identifier":"https:\/\/www.braze.com\/docs\/user_guide\/message_building_by_channel\/content_cards\/"},{"text":" to your users using the Braze provided user interface.","type":"text"}],"url":"\/tutorials\/braze\/c2-contentcardsui#BrazeContentCardsUI","identifier":"doc:\/\/Braze\/tutorials\/Braze\/c2-contentcardsui#BrazeContentCardsUI","role":"pseudoSymbol","type":"section","title":"BrazeContentCardsUI","kind":"section"},"https://www.braze.com/docs/user_guide/message_building_by_channel/content_cards/":{"identifier":"https:\/\/www.braze.com\/docs\/user_guide\/message_building_by_channel\/content_cards\/","type":"link","title":"Content Cards","url":"https:\/\/www.braze.com\/docs\/user_guide\/message_building_by_channel\/content_cards\/","titleInlineContent":[{"type":"text","text":"Content Cards"}]},"doc://Braze/tutorials/Braze/b4-live-activities#Resuming-Live-Activity-tracking":{"title":"Resuming Live Activity tracking","url":"\/tutorials\/braze\/b4-live-activities#Resuming-Live-Activity-tracking","type":"section","abstract":[{"type":"text","text":"Learn how to remotely track and manage your iOS "},{"type":"reference","identifier":"https:\/\/developer.apple.com\/documentation\/activitykit\/updating-and-ending-your-live-activity-with-activitykit-push-notifications","isActive":true},{"type":"text","text":" with Braze push notifications."}],"role":"pseudoSymbol","kind":"section","identifier":"doc:\/\/Braze\/tutorials\/Braze\/b4-live-activities#Resuming-Live-Activity-tracking"},"doc://Braze/tutorials/Braze/a1-installation#Braze-Swift-Package":{"abstract":[{"type":"text","text":"Install the SDK using the Swift Package Manager."}],"kind":"section","role":"pseudoSymbol","identifier":"doc:\/\/Braze\/tutorials\/Braze\/a1-installation#Braze-Swift-Package","type":"section","title":"Braze Swift Package","url":"\/tutorials\/braze\/a1-installation#Braze-Swift-Package"},"doc://Braze/tutorials/00-integration-path/Braze-Essentials":{"role":"article","url":"\/tutorials\/00-integration-path\/braze-essentials","kind":"article","identifier":"doc:\/\/Braze\/tutorials\/00-integration-path\/Braze-Essentials","type":"topic","title":"Braze Essentials","abstract":[]},"doc://Braze/tutorials/Braze/b2-rich-push-notifications#Notification-Service-Extension":{"role":"pseudoSymbol","identifier":"doc:\/\/Braze\/tutorials\/Braze\/b2-rich-push-notifications#Notification-Service-Extension","type":"section","abstract":[{"text":"Learn how to support receiving rich push notifications with images, audio and video.","type":"text"}],"title":"Notification Service Extension","url":"\/tutorials\/braze\/b2-rich-push-notifications#Notification-Service-Extension","kind":"section"},"doc://Braze/documentation/Braze/gif-support-integrations":{"identifier":"doc:\/\/Braze\/documentation\/Braze\/gif-support-integrations","abstract":[{"identifier":"doc:\/\/Braze\/documentation\/BrazeUI\/GIFViewProvider","isActive":true,"type":"reference"},{"type":"text","text":" implementations for common third party GIF images libraries."}],"url":"\/documentation\/braze\/gif-support-integrations","title":"GIF Support Integrations","role":"article","type":"topic","kind":"article"},"doc://Braze/tutorials/Braze/b4-live-activities#Setting-up-push-to-start":{"abstract":[{"type":"text","text":"Learn how to remotely track and manage your iOS "},{"identifier":"https:\/\/developer.apple.com\/documentation\/activitykit\/updating-and-ending-your-live-activity-with-activitykit-push-notifications","isActive":true,"type":"reference"},{"type":"text","text":" with Braze push notifications."}],"url":"\/tutorials\/braze\/b4-live-activities#Setting-up-push-to-start","kind":"section","type":"section","title":"Setting up push-to-start","identifier":"doc:\/\/Braze\/tutorials\/Braze\/b4-live-activities#Setting-up-push-to-start","role":"pseudoSymbol"},"doc://Braze/tutorials/Braze/a3-analytics#Identify-the-current-user":{"url":"\/tutorials\/braze\/a3-analytics#Identify-the-current-user","kind":"section","title":"Identify the current user","role":"pseudoSymbol","abstract":[{"type":"text","text":"Learn how to log user attributes, custom events, purchases."}],"identifier":"doc:\/\/Braze\/tutorials\/Braze\/a3-analytics#Identify-the-current-user","type":"section"},"https://www.braze.com/docs/user_guide/message_building_by_channel/in-app_messages":{"url":"https:\/\/www.braze.com\/docs\/user_guide\/message_building_by_channel\/in-app_messages","title":"In-App Messages","identifier":"https:\/\/www.braze.com\/docs\/user_guide\/message_building_by_channel\/in-app_messages","type":"link","titleInlineContent":[{"type":"text","text":"In-App Messages"}]},"doc://Braze/tutorials/Braze/a1-installation":{"estimatedTime":"5min","type":"topic","abstract":[{"type":"text","text":"Install the SDK using the Swift Package Manager."}],"title":"Installation","url":"\/tutorials\/braze\/a1-installation","kind":"project","identifier":"doc:\/\/Braze\/tutorials\/Braze\/a1-installation","role":"project"},"doc://Braze/tutorials/Braze/b4-live-activities#Creating-a-Live-Activity":{"type":"section","title":"Creating a Live Activity","url":"\/tutorials\/braze\/b4-live-activities#Creating-a-Live-Activity","identifier":"doc:\/\/Braze\/tutorials\/Braze\/b4-live-activities#Creating-a-Live-Activity","abstract":[{"text":"Learn how to remotely track and manage your iOS ","type":"text"},{"identifier":"https:\/\/developer.apple.com\/documentation\/activitykit\/updating-and-ending-your-live-activity-with-activitykit-push-notifications","isActive":true,"type":"reference"},{"text":" with Braze push notifications.","type":"text"}],"role":"pseudoSymbol","kind":"section"},"doc://Braze/tutorials/00-integration-path/Location":{"title":"Location","identifier":"doc:\/\/Braze\/tutorials\/00-integration-path\/Location","role":"article","type":"topic","url":"\/tutorials\/00-integration-path\/location","abstract":[],"kind":"article"},"doc://Braze/tutorials/Braze/d1-brazelocation#BrazeLocationProvider":{"role":"pseudoSymbol","title":"BrazeLocationProvider","url":"\/tutorials\/braze\/d1-brazelocation#BrazeLocationProvider","abstract":[{"text":"Learn how to implement ","type":"text"},{"isActive":true,"type":"reference","identifier":"https:\/\/www.braze.com\/docs\/user_guide\/engagement_tools\/locations_and_geofences\/"},{"text":" using the ","type":"text"},{"type":"strong","inlineContent":[{"text":"BrazeLocation","type":"text"}]},{"text":" module.","type":"text"}],"type":"section","identifier":"doc:\/\/Braze\/tutorials\/Braze\/d1-brazelocation#BrazeLocationProvider","kind":"section"},"https://www.braze.com/docs/user_guide/engagement_tools/locations_and_geofences/":{"identifier":"https:\/\/www.braze.com\/docs\/user_guide\/engagement_tools\/locations_and_geofences\/","type":"link","title":"location analytics and geofence monitoring","url":"https:\/\/www.braze.com\/docs\/user_guide\/engagement_tools\/locations_and_geofences\/","titleInlineContent":[{"type":"text","text":"location analytics and geofence monitoring"}]},"doc://Braze/tutorials/Braze/b1-standard-push-notifications":{"role":"project","estimatedTime":"20min","type":"topic","kind":"project","title":"Standard Push Notifications","identifier":"doc:\/\/Braze\/tutorials\/Braze\/b1-standard-push-notifications","url":"\/tutorials\/braze\/b1-standard-push-notifications","abstract":[{"text":"Learn how to support receiving foreground and background push notifications.","type":"text"}]},"doc://Braze/tutorials/Braze/c3-gif-support":{"identifier":"doc:\/\/Braze\/tutorials\/Braze\/c3-gif-support","type":"topic","abstract":[{"type":"text","text":"Learn how to add GIF images support to Braze provided user interface using third party libraries."}],"title":"GIF Support","role":"project","estimatedTime":"5min","url":"\/tutorials\/braze\/c3-gif-support","kind":"project"},"doc://Braze/tutorials/Braze/c2-contentcardsui#Optional-Content-Cards-customization":{"url":"\/tutorials\/braze\/c2-contentcardsui#Optional-Content-Cards-customization","title":"Optional: Content Cards customization","role":"pseudoSymbol","abstract":[{"type":"text","text":"Learn how to display "},{"identifier":"https:\/\/www.braze.com\/docs\/user_guide\/message_building_by_channel\/content_cards\/","type":"reference","isActive":true},{"type":"text","text":" to your users using the Braze provided user interface."}],"type":"section","kind":"section","identifier":"doc:\/\/Braze\/tutorials\/Braze\/c2-contentcardsui#Optional-Content-Cards-customization"},"doc://Braze/tutorials/00-integration-path/Push-Notifications":{"identifier":"doc:\/\/Braze\/tutorials\/00-integration-path\/Push-Notifications","url":"\/tutorials\/00-integration-path\/push-notifications","role":"article","title":"Push Notifications","kind":"article","type":"topic","abstract":[]},"doc://Braze/tutorials/Braze/b1-standard-push-notifications#Option-1-Automatic-push-notification-handling":{"kind":"section","role":"pseudoSymbol","abstract":[{"text":"Learn how to support receiving foreground and background push notifications.","type":"text"}],"title":"Option 1: Automatic push notification handling","identifier":"doc:\/\/Braze\/tutorials\/Braze\/b1-standard-push-notifications#Option-1-Automatic-push-notification-handling","url":"\/tutorials\/braze\/b1-standard-push-notifications#Option-1-Automatic-push-notification-handling","type":"section"},"doc://Braze/tutorials/Braze/b1-standard-push-notifications#Option-2-Implement-the-push-notification-handlers-manually":{"url":"\/tutorials\/braze\/b1-standard-push-notifications#Option-2-Implement-the-push-notification-handlers-manually","role":"pseudoSymbol","title":"Option 2: Implement the push notification handlers manually","type":"section","identifier":"doc:\/\/Braze\/tutorials\/Braze\/b1-standard-push-notifications#Option-2-Implement-the-push-notification-handlers-manually","abstract":[{"type":"text","text":"Learn how to support receiving foreground and background push notifications."}],"kind":"section"}}}